rpa_arc/__init__.py
rpa_arc/cli.py
rpa_arc/conteudos.py
rpa_arc/estrutura.py
rpa_arc-0.7.0.dist-info/licenses/LICENSE
rpa_arc-0.7.0.dist-info/METADATA
rpa_arc-0.7.0.dist-info/WHEEL
rpa_arc-0.7.0.dist-info/entry_points.txt
rpa_arc-0.7.0.dist-info/top_level.txt
rpa_arc-0.7.0.dist-info/RECORD
