Metadata-Version: 2.4
Name: rpa-arc
Version: 0.7.0
Summary: CLI para geração de estrutura de projetos RPA
Author: Luis Henrique
Author-email: Seu Nome <seu@email.com>
Requires-Python: >=3.7
License-File: LICENSE
Requires-Dist: requests<3,>=2.28
Requires-Dist: python-dotenv<2,>=1.0
Requires-Dist: selenium<5,>=4.0
Requires-Dist: webdriver-manager<5,>=4.0
Dynamic: author
Dynamic: license-file
Dynamic: requires-python
